README.md
setup.py
cursed_lich/__init__.py
cursed_lich/bin.py
cursed_lich/client.py
cursed_lich/config.py
cursed_lich/db.py
cursed_lich/default_server_config.py
cursed_lich/display.py
cursed_lich/error.py
cursed_lich/model.py
cursed_lich/net_pb2.py
cursed_lich/server.py
cursed_lich/terrain.py
cursed_lich.egg-info/PKG-INFO
cursed_lich.egg-info/SOURCES.txt
cursed_lich.egg-info/dependency_links.txt
cursed_lich.egg-info/entry_points.txt
cursed_lich.egg-info/requires.txt
cursed_lich.egg-info/top_level.txt