Metadata-Version: 1.1
Name: cursed-lich
Version: 0.1.1
Summary: NCurses MMO, one of its kind! The Undead Empire strikes.
Home-page: https://bitbucket.org/johannestaas/cursed_lich
Author: Johan Nestaas
Author-email: johannestaas@gmail.com
License: GPLv3+
Keywords: cli war mmo console ncurses magic lich undead
Platform: UNKNOWN
Classifier: Development Status :: 2 - Pre-Alpha
Classifier: License :: OSI Approved :: GNU General Public License v3 or later (GPLv3+)
Classifier: Environment :: Console
Classifier: Environment :: MacOS X
Classifier: Environment :: Win32 (MS Windows)
Classifier: Operating System :: POSIX
Classifier: Operating System :: MacOS :: MacOS X
Classifier: Operating System :: Microsoft :: Windows
Classifier: Programming Language :: Python
